{
  "_class": "shapePath",
  "booleanOperation": -1,
  "do_objectID": "D62C2C39-CB5B-48F5-96F7-FD9B153DD2A7",
  "edited": true,
  "exportOptions": {
    "_class": "exportOptions",
    "exportFormats": [
    ],
    "includedLayerIds": [
    ],
    "layerOptions": 0,
    "shouldTrim": false
  },
  "frame": {
    "_class": "rect",
    "constrainProportions": false,
    "height": 3.457002853141249,
    "width": 2.415447849343782,
    "x": -3.469446951953614e-17,
    "y": 1.178198907874277
  },
  "isFlippedHorizontal": false,
  "isFlippedVertical": false,
  "isLocked": false,
  "isVisible": true,
  "layerListExpandedType": 0,
  "name": "Fill-14-Copy-path",
  "nameIsFixed": false,
  "path": {
    "_class": "path",
    "isClosed": true,
    "pointRadiusBehaviour": 1,
    "points": [
      {
        "_class": "curvePoint",
        "cornerRadius": 0,
        "curveFrom": "{0.45138872057817636, 0.25414088772458998}",
        "curveMode": 4,
        "curveTo": "{0.45138872057817636, 0.29080542779100527}",
        "hasCurveFrom": true,
        "hasCurveTo": false,
        "point": "{0.45138872057817636, 0.29080542779100527}"
      },
      {
        "_class": "curvePoint",
        "cornerRadius": 0,
        "curveFrom": "{0.61068775625860894, 0.23581555418591682}",
        "curveMode": 3,
        "curveTo": "{0.49097328195938483, 0.23581555418591682}",
        "hasCurveFrom": true,
        "hasCurveTo": true,
        "point": "{0.57033456275292149, 0.23581555418591682}"
      },
      {
        "_class": "curvePoint",
        "cornerRadius": 0,
        "curveFrom": "{0.75038666977745305, 0.26003662350833029}",
        "curveMode": 2,
        "curveTo": "{0.65507626941360264, 0.2406986104716323}",
        "hasCurveFrom": true,
        "hasCurveTo": true,
        "point": "{0.70330794418678311, 0.25064506355170085}"
      },
      {
        "_class": "curvePoint",
        "cornerRadius": 0,
        "curveFrom": "{0.87836394140640961, 0.22061149220533133}",
        "curveMode": 2,
        "curveTo": "{0.79477518293244676, 0.25598590621200207}",
        "hasCurveFrom": true,
        "hasCurveTo": true,
        "point": "{0.83608916758952501, 0.23857614542250055}"
      },
      {
        "_class": "curvePoint",
        "cornerRadius": 0,
        "curveFrom": "{0.91352886608028017, 0.16599617121504445}",
        "curveMode": 4,
        "curveTo": "{0.90411312255541365, 0.19629331682983608}",
        "hasCurveFrom": false,
        "hasCurveTo": true,
        "point": "{0.91352886608028017, 0.16599617121504445}"
      },
      {
        "_class": "curvePoint",
        "cornerRadius": 0,
        "curveFrom": "{0.92621129613418163, 0.13264711620442363}",
        "curveMode": 4,
        "curveTo": "{0.91487397229811807, 0.16498349241279103}",
        "hasCurveFrom": true,
        "hasCurveTo": false,
        "point": "{0.91487397229811807, 0.16498349241279103}"
      },
      {
        "_class": "curvePoint",
        "cornerRadius": 0,
        "curveFrom": "{0.87394430569486392, 0.048178564376404893}",
        "curveMode": 4,
        "curveTo": "{0.92044655520058993, 0.1028077576599893}",
        "hasCurveFrom": true,
        "hasCurveTo": true,
        "point": "{0.89815622259491013, 0.075534777550203533}"
      },
      {
        "_class": "curvePoint",
        "cornerRadius": 0,
        "curveFrom": "{0.7165668503256285, 0.007185861147713378}",
        "curveMode": 3,
        "curveTo": "{0.83877938002520114, 0.030116804410382374}",
        "hasCurveFrom": true,
        "hasCurveTo": true,
        "point": "{0.79227712852789045, 0.021377243630273837}"
      },
      {
        "_class": "curvePoint",
        "cornerRadius": 0,
        "curveFrom": "{0.39258835210182663, 0}",
        "curveMode": 3,
        "curveTo": "{0.63778204362545088, 0}",
        "hasCurveFrom": true,
        "hasCurveTo": true,
        "point": "{0.55611486645847752, 0}"
      },
      {
        "_class": "curvePoint",
        "cornerRadius": 0,
        "curveFrom": "{0.055927421832538654, 0.15162444891961774}",
        "curveMode": 4,
        "curveTo": "{0.25903849657460581, 0.030491357025183779}",
        "hasCurveFrom": true,
        "hasCurveTo": true,
        "point": "{0.15584961593905464, 0.091293732654228146}"
      },
      {
        "_class": "curvePoint",
        "cornerRadius": 0,
        "curveFrom": "{0.0026996377523492827, 0.45422134479924592}",
        "curveMode": 4,
        "curveTo": "{0.0059663248788599148, 0.2279915661549799}",
        "hasCurveFrom": true,
        "hasCurveTo": true,
        "point": "{0.0059663248788599148, 0.32056155257565511}"
      },
      {
        "_class": "curvePoint",
        "cornerRadius": 0,
        "curveFrom": "{0.45965151691211664, 0.63153733448006033}",
        "curveMode": 4,
        "curveTo": "{0.13086906691452951, 0.55204894081620937}",
        "hasCurveFrom": true,
        "hasCurveTo": true,
        "point": "{0.39066677179062942, 0.61412757160324405}"
      },
      {
        "_class": "curvePoint",
        "cornerRadius": 0,
        "curveFrom": "{0.54650696291090706, 0.67004689164234454}",
        "curveMode": 4,
        "curveTo": "{0.50519297825382881, 0.64646394433275367}",
        "hasCurveFrom": true,
        "hasCurveTo": true,
        "point": "{0.52767547187800523, 0.65889354834963054}"
      },
      {
        "_class": "curvePoint",
        "cornerRadius": 0,
        "curveFrom": "{0.55611486645847752, 0.74244652116653365}",
        "curveMode": 3,
        "curveTo": "{0.55611486645847752, 0.68523708063386102}",
        "hasCurveFrom": true,
        "hasCurveTo": true,
        "point": "{0.55611486645847752, 0.70458896457231346}"
      },
      {
        "_class": "curvePoint",
        "cornerRadius": 0,
        "curveFrom": "{0.36338032639266765, 0.76142385736058549}",
        "curveMode": 3,
        "curveTo": "{0.51038124608985347, 0.76142385736058549}",
        "hasCurveFrom": true,
        "hasCurveTo": true,
        "point": "{0.41910616537530954, 0.76142385736058549}"
      },
      {
        "_class": "curvePoint",
        "cornerRadius": 0,
        "curveFrom": "{0.17910074168770995, 0.72660433856466855}",
        "curveMode": 4,
        "curveTo": "{0.2995838491072052, 0.75330855186617462}",
        "hasCurveFrom": true,
        "hasCurveTo": true,
        "point": "{0.22810104858536934, 0.73710568128931864}"
      },
      {
        "_class": "curvePoint",
        "cornerRadius": 0,
        "curveFrom": "{0.04612736025384833, 0.76473934102483676}",
        "curveMode": 2,
        "curveTo": "{0.1329828062526387, 0.7300030573802474}",
        "hasCurveFrom": true,
        "hasCurveTo": true,
        "point": "{0.089939399315482962, 0.74741281329934817}"
      },
      {
        "_class": "curvePoint",
        "cornerRadius": 0,
        "curveFrom": "{0.0048133764929831294, 0.82572205507520435}",
        "curveMode": 4,
        "curveTo": "{0.017880124700287957, 0.79090253627928753}",
        "hasCurveFrom": false,
        "hasCurveTo": true,
        "point": "{0.0048133764929831294, 0.82572205507520435}"
      },
      {
        "_class": "curvePoint",
        "cornerRadius": 0,
        "curveFrom": "{-0.0053710009487881851, 0.85675443362630144}",
        "curveMode": 4,
        "curveTo": "{0.0048133764929831294, 0.82755320057354753}",
        "hasCurveFrom": true,
        "hasCurveTo": false,
        "point": "{0.0048133764929831294, 0.82755320057354753}"
      },
      {
        "_class": "curvePoint",
        "cornerRadius": 0,
        "curveFrom": "{0.045166570098249724, 0.94159754085220793}",
        "curveMode": 4,
        "curveTo": "{0.00058589901171544748, 0.88567822081310732}",
        "hasCurveFrom": true,
        "hasCurveTo": true,
        "point": "{0.022876234505192973, 0.91424132698263771}"
      },
      {
        "_class": "curvePoint",
        "cornerRadius": 0,
        "curveFrom": "{0.21599509063324232, 0.9899564471287936}",
        "curveMode": 4,
        "curveTo": "{0.078409915456715135, 0.96020032234414376}",
        "hasCurveFrom": true,
        "hasCurveTo": true,
        "point": "{0.12222195451834977, 0.97014677333689758}"
      },
      {
        "_class": "curvePoint",
        "cornerRadius": 0,
        "curveFrom": "{0.60415438220474615, 1}",
        "curveMode": 3,
        "curveTo": "{0.31514865161948719, 1}",
        "hasCurveFrom": true,
        "hasCurveTo": true,
        "point": "{0.41910616537530954, 1}"
      },
      {
        "_class": "curvePoint",
        "cornerRadius": 0,
        "curveFrom": "{0.95099969210654822, 0.85242626837671054}",
        "curveMode": 2,
        "curveTo": "{0.74884940552849533, 0.96986932747094967}",
        "hasCurveFrom": true,
        "hasCurveTo": true,
        "point": "{0.85280691928431762, 0.90963571586709857}"
      },
      {
        "_class": "curvePoint",
        "cornerRadius": 0,
        "curveFrom": "{0.99750194559544347, 0.54117304338944339}",
        "curveMode": 4,
        "curveTo": "{1, 0.77661404635210196}",
        "hasCurveFrom": true,
        "hasCurveTo": true,
        "point": "{1, 0.68219904283555777}"
      },
      {
        "_class": "curvePoint",
        "cornerRadius": 0,
        "curveFrom": "{0.55995802708087206, 0.36191493264699287}",
        "curveMode": 3,
        "curveTo": "{0.87644236109521234, 0.4407651994276201}",
        "hasCurveFrom": true,
        "hasCurveTo": true,
        "point": "{0.63739772756321156, 0.38116971470699279}"
      },
      {
        "_class": "curvePoint",
        "cornerRadius": 0,
        "curveFrom": "{0.46253388837470472, 0.32157423137790858}",
        "curveMode": 4,
        "curveTo": "{0.50903613987201546, 0.34571206902785234}",
        "hasCurveFrom": true,
        "hasCurveTo": true,
        "point": "{0.4850163819988812, 0.33271370376886827}"
      },
      {
        "_class": "curvePoint",
        "cornerRadius": 0,
        "curveFrom": "{0.45138872057817636, 0.29080542779100527}",
        "curveMode": 4,
        "curveTo": "{0.45138872057817636, 0.30757706169728316}",
        "hasCurveFrom": false,
        "hasCurveTo": true,
        "point": "{0.45138872057817636, 0.29080542779100527}"
      }
    ]
  },
  "resizingConstraint": 63,
  "resizingType": 0,
  "rotation": 0,
  "shouldBreakMaskChain": false
}