{
  "_class": "shapePath",
  "booleanOperation": -1,
  "do_objectID": "FA952056-F3EA-4724-A06D-AA4CA805B52C",
  "edited": true,
  "exportOptions": {
    "_class": "exportOptions",
    "exportFormats": [
    ],
    "includedLayerIds": [
    ],
    "layerOptions": 0,
    "shouldTrim": false
  },
  "frame": {
    "_class": "rect",
    "constrainProportions": false,
    "height": 4.435529620585879,
    "width": 3.795318923762588,
    "x": 3.767816612720823,
    "y": 0.6205463818404435
  },
  "isFlippedHorizontal": false,
  "isFlippedVertical": false,
  "isLocked": false,
  "isVisible": true,
  "layerListExpandedType": 0,
  "name": "Path",
  "nameIsFixed": false,
  "path": {
    "_class": "path",
    "isClosed": true,
    "pointRadiusBehaviour": 0,
    "points": [
      {
        "_class": "curvePoint",
        "cornerRadius": 0,
        "curveFrom": "{0.96301984229570559, 0.98416232483060873}",
        "curveMode": 4,
        "curveTo": "{1, 1}",
        "hasCurveFrom": true,
        "hasCurveTo": false,
        "point": "{1, 1}"
      },
      {
        "_class": "curvePoint",
        "cornerRadius": 0,
        "curveFrom": "{0.83945761138215413, 0.95251458681595491}",
        "curveMode": 4,
        "curveTo": "{0.92420321898587843, 0.97103492862820318}",
        "hasCurveFrom": true,
        "hasCurveTo": true,
        "point": "{0.88405797101449268, 0.96078955815256983}"
      },
      {
        "_class": "curvePoint",
        "cornerRadius": 0,
        "curveFrom": "{0.67369641106000999, 0.94581002501022704}",
        "curveMode": 4,
        "curveTo": "{0.79398435240128185, 0.94735909282793984}",
        "hasCurveFrom": true,
        "hasCurveTo": true,
        "point": "{0.74818840579710133, 0.94538545599822232}"
      },
      {
        "_class": "curvePoint",
        "cornerRadius": 0,
        "curveFrom": "{0.45785501883884749, 0.93634110705577001}",
        "curveMode": 4,
        "curveTo": "{0.59929786898717285, 0.94955054588950505}",
        "hasCurveFrom": true,
        "hasCurveTo": true,
        "point": "{0.52536231884057949, 0.95658843938320237}"
      },
      {
        "_class": "curvePoint",
        "cornerRadius": 0,
        "curveFrom": "{0.23601744840772623, 0.77291641598711081}",
        "curveMode": 4,
        "curveTo": "{0.39626258454010577, 0.90586986721694751}",
        "hasCurveFrom": true,
        "hasCurveTo": true,
        "point": "{0.34420289855072439, 0.86696457230336166}"
      },
      {
        "_class": "curvePoint",
        "cornerRadius": 0,
        "curveFrom": "{0.1306128383826472, 0.44804459098186389}",
        "curveMode": 4,
        "curveTo": "{0.15619785716134749, 0.66147195378428914}",
        "hasCurveFrom": true,
        "hasCurveTo": true,
        "point": "{0.11050724637681182, 0.54067768121581672}"
      },
      {
        "_class": "curvePoint",
        "cornerRadius": 0,
        "curveFrom": "{0.15022454894020129, 0.22564560954244076}",
        "curveMode": 4,
        "curveTo": "{0.14271690590104394, 0.35447944054536207}",
        "hasCurveFrom": true,
        "hasCurveTo": true,
        "point": "{0.14673913043478304, 0.26060309659131464}"
      },
      {
        "_class": "curvePoint",
        "cornerRadius": 0,
        "curveFrom": "{0.15927840234577723, 0.11237583061816726}",
        "curveMode": 4,
        "curveTo": "{0.15022454894020129, 0.19053261440600025}",
        "hasCurveFrom": true,
        "hasCurveTo": true,
        "point": "{0.14673913043478304, 0.15557512735712636}"
      },
      {
        "_class": "curvePoint",
        "cornerRadius": 0,
        "curveFrom": "{0.081012661194557994, 0.01026221344526506}",
        "curveMode": 4,
        "curveTo": "{0.14596930389240326, 0.067108582173671397}",
        "hasCurveFrom": true,
        "hasCurveTo": true,
        "point": "{0.11050724637681214, 0.032342310122345494}"
      },
      {
        "_class": "curvePoint",
        "cornerRadius": 0,
        "curveFrom": "{0, 0.00013373289052763814}",
        "curveMode": 4,
        "curveTo": "{0.041011093068200472, -0.0013966925417539825}",
        "hasCurveFrom": false,
        "hasCurveTo": true,
        "point": "{0, 0.00013373289052763814}"
      },
      {
        "_class": "curvePoint",
        "cornerRadius": 0,
        "curveFrom": "{0.45652173913043476, 0.00013373289052763814}",
        "curveMode": 1,
        "curveTo": "{0.45652173913043476, 0.00013373289052763814}",
        "hasCurveFrom": false,
        "hasCurveTo": false,
        "point": "{0.45652173913043476, 0.00013373289052763814}"
      },
      {
        "_class": "curvePoint",
        "cornerRadius": 0,
        "curveFrom": "{1, 0.42024560982728065}",
        "curveMode": 1,
        "curveTo": "{1, 0.42024560982728065}",
        "hasCurveFrom": false,
        "hasCurveTo": false,
        "point": "{1, 0.42024560982728065}"
      },
      {
        "_class": "curvePoint",
        "cornerRadius": 0,
        "curveFrom": "{1, 0.99859962707687755}",
        "curveMode": 1,
        "curveTo": "{1, 0.99859962707687755}",
        "hasCurveFrom": false,
        "hasCurveTo": false,
        "point": "{1, 0.99859962707687755}"
      },
      {
        "_class": "curvePoint",
        "cornerRadius": 0,
        "curveFrom": "{1, 0.99859962707687755}",
        "curveMode": 1,
        "curveTo": "{1, 0.99859962707687755}",
        "hasCurveFrom": false,
        "hasCurveTo": false,
        "point": "{1, 0.99859962707687755}"
      }
    ]
  },
  "resizingConstraint": 63,
  "resizingType": 0,
  "rotation": 0,
  "shouldBreakMaskChain": false
}